mlservice/__init__.py
mlservice/core/__init__.py
mlservice/core/ml.py
mlservice/core/registry.py
mlservice/core/router.py
mlservice/core/tabml.py
mlservice/core/upload_routes.py
mlservice/core/utils.py
mlservice/main.py
pymlservice-0.1.1.dist-info/METADATA
pymlservice-0.1.1.dist-info/WHEEL
pymlservice-0.1.1.dist-info/RECORD
