Metadata-Version: 2.1
Name: pymlservice
Version: 0.1.1
Summary: 
Author: Bo Chen
Author-email: bochen0909@gmail.com
Requires-Python: >3.10
Classifier: Programming Language :: Python :: 3
Classifier: Programming Language :: Python :: 3.11
Classifier: Programming Language :: Python :: 3.12
Classifier: Programming Language :: Python :: 3.13
Requires-Dist: fastapi (>=0.115.7,<0.116.0)
Requires-Dist: joblib (>=1.4.2,<2.0.0)
Requires-Dist: pandas (>=2.2.3,<3.0.0)
Requires-Dist: python-multipart (>=0.0.20,<0.0.21)
Requires-Dist: scikit-learn (>=1.6.1,<2.0.0)
Requires-Dist: uvicorn (>=0.34.0,<0.35.0)
